LICENSE.txt
README.rst
setup.py
rocket_ichraq/__init__.py
rocket_ichraq/rocket.py
rocket_ichraq.egg-info/PKG-INFO
rocket_ichraq.egg-info/SOURCES.txt
rocket_ichraq.egg-info/dependency_links.txt
rocket_ichraq.egg-info/requires.txt
rocket_ichraq.egg-info/top_level.txt