Metadata-Version: 2.1
Name: rocket_ichraq
Version: 1.0.0
Summary: An awesome package that does something
Home-page: http://pypi.python.org/pypi/rocket_ichraq/
Author: ichraq
Author-email: zi.amieur@esi-sba.dz
License: LICENSE.txt
License-File: LICENSE.txt
Requires-Dist: rocket_ichraq
